Workbook

Sheet 投档表
B1: 山东省2025年普通类常规批第1次志愿投档情况表
A2: 代码 | B2: 专业 | C2: 院校 | D2: 投档计划数 | E2: 投档最低位次 | F2: 投档最低分数
A3: =LEFT(C3,4)&LEFT(B3,2) -> A0031C | B3: 1C文科试验班类(文科各专业) | C3: A003清华大学 | D3: 3 | E3: 50 | F3: {=INDEX(一分一段!A:A,MATCH(TRUE,(一分一段!B:B>=E3),0))} -> 692
A4: =LEFT(C4,4)&LEFT(B4,2) -> A0031A | B4: 1A临床医学类 | C4: A003清华大学 | D4: 5 | E4: 109 | F4: {=INDEX(一分一段!A:A,MATCH(TRUE,(一分一段!B:B>=E4),0))} -> 687
A5: =LEFT(C5,4)&LEFT(B5,2) -> A00156 | B5: 56理科试验班类(理科基础类专业) | C5: A001北京大学 | D5: 50 | E5: 138 | F5: {=INDEX(一分一段!A:A,MATCH(TRUE,(一分一段!B:B>=E5),0))} -> 685
A6: =LEFT(C6,4)&LEFT(B6,2) -> A0031B | B6: 1B理科试验班(理科各专业) | C6: A003清华大学 | D6: 72 | E6: 140 | F6: {=INDEX(一分一段!A:A,MATCH(TRUE,(一分一段!B:B>=E6),0))} -> 685
A7: =LEFT(C7,4)&LEFT(B7,2) -> A00117 | B7: 17文科试验班类(不限选考科目类专业) | C7: A001北京大学 | D7: 22 | E7: 178 | F7: {=INDEX(一分一段!A:A,MATCH(TRUE,(一分一段!B:B>=E7),0))} -> 684
A8: =LEFT(C8,4)&LEFT(B8,2) -> A24849 | B8: 49电子信息类(计算机永强试验班) | C8: A248上海交通大学 | D8: 1 | E8: 192 | F8: {=INDEX(一分一段!A:A,MATCH(TRUE,(一分一段!B:B>=E8),0))} -> 683
A9: =LEFT(C9,4)&LEFT(B9,2) -> A24850 | B9: 50电子信息类(集成电路英才班) | C9: A248上海交通大学 | D9: 1 | E9: 198 | F9: {=INDEX(一分一段!A:A,MATCH(TRUE,(一分一段!B:B>=E9),0))} -> 683
A10: =LEFT(C10,4)&LEFT(B10,2) -> A24634 | B10: 34工科试验班(相辉学堂香农计划) | C10: A246复旦大学 | D10: 2 | E10: 203 | F10: {=INDEX(一分一段!A:A,MATCH(TRUE,(一分一段!B:B>=E10),0))} -> 683
A11: =LEFT(C11,4)&LEFT(B11,2) -> H00104 | B11: 04口腔医学(八年制本博连读) | C11: H001北京大学医学部 | D11: 1 | E11: 204 | F11: {=INDEX(一分一段!A:A,MATCH(TRUE,(一分一段!B:B>=E11),0))} -> 683
A12: =LEFT(C12,4)&LEFT(B12,2) -> E4300U | B12: 0U人工智能 | C12: E430中国科学院大学 | D12: 2 | E12: 212 | F12: {=INDEX(一分一段!A:A,MATCH(TRUE,(一分一段!B:B>=E12),0))} -> 682
A13: =LEFT(C13,4)&LEFT(B13,2) -> A24635 | B13: 35工科试验班(集成电路领军人才班) | C13: A246复旦大学 | D13: 3 | E13: 218 | F13: {=INDEX(一分一段!A:A,MATCH(TRUE,(一分一段!B:B>=E13),0))} -> 682
A14: =LEFT(C14,4)&LEFT(B14,2) -> H00102 | B14: 02临床医学(八年制本博连读) | C14: H001北京大学医学部 | D14: 11 | E14: 221 | F14: {=INDEX(一分一段!A:A,MATCH(TRUE,(一分一段!B:B>=E14),0))} -> 682
... A21383: =LEFT(C21383,4)&LEFT(B21383,2) -> D37806 | B21383: 06网络工程 | C21383: D378青岛城市学院 | D21383: 35 | E21383: 333415 | F21383: {=INDEX(一分一段!A:A,MATCH(TRUE,(一分一段!B:B>=E21383),0))} -> 441

Sheet 一分一段
A1: 692 | B1: 54
A2: 691 | B2: 68
A3: 690 | B3: 80
A4: 689 | B4: 93
A5: 688 | B5: 106
A6: 687 | B6: 119
A7: 686 | B7: 135
A8: 685 | B8: 155
A9: 684 | B9: 181
A10: 683 | B10: 211
A11: 682 | B11: 246
A12: 681 | B12: 289
... A543: 150 | B543: 681127
